galeritas/__init__.py
galeritas/bar_plot_with_population_proportion.py
galeritas/plot_calibration_and_distribution.py
galeritas/plot_ecdf_curve.py
galeritas/plot_ks_classification.py
galeritas/precision_and_recall_by_probability_threshold.py
galeritas/precision_recall_threshold_confidence_interval_aux.py
galeritas/stacked_percentage_bar_plot.py
galeritas/utils/__init__.py
galeritas/utils/creditas_palette.py
tests/__init__.py
tests/test_bar_plot_with_population_proportion.py
tests/test_plot_calibration_and_distribution.py
tests/test_plot_ecdf_curve.py
tests/test_plot_ks_classification.py
tests/test_precision_and_recall_by_probability_threshold.py
tests/test_stacked_percentage_bar_plot.py
galeritas-0.2.0.dist-info/LICENSE
galeritas-0.2.0.dist-info/METADATA
galeritas-0.2.0.dist-info/WHEEL
galeritas-0.2.0.dist-info/top_level.txt
galeritas-0.2.0.dist-info/RECORD
