Metadata-Version: 2.1
Name: galeritas
Version: 0.2.0
Summary: UNKNOWN
Home-page: https://github.com/Creditas/galeritas/
Author: Creditas Data Science Team
Author-email: data-science@creditas.com
License: UNKNOWN
Platform: UNKNOWN
Classifier: Programming Language :: Python :: 3
Classifier: Operating System :: OS Independent
Requires-Python: >=3.6.9
Requires-Dist: numpy (>=1.15)
Requires-Dist: scipy (>=1.4.1)
Requires-Dist: pandas (>=1.0.3)
Requires-Dist: scikit-learn (>=0.20.4)
Requires-Dist: seaborn (>=0.11.0)
Requires-Dist: pytest (>=6.1.2)
Requires-Dist: pytest-mpl (>=0.12.0)
Requires-Dist: matplotlib (>=3.3.3)
